chuk_acp/__init__.py
chuk_acp/cli.py
chuk_acp/py.typed
chuk_acp/agent/__init__.py
chuk_acp/agent/agent.py
chuk_acp/agent/models.py
chuk_acp/client/__init__.py
chuk_acp/client/client.py
chuk_acp/client/config.py
chuk_acp/client/models.py
chuk_acp/protocol/__init__.py
chuk_acp/protocol/acp_pydantic_base.py
chuk_acp/protocol/constants.py
chuk_acp/protocol/jsonrpc.py
chuk_acp/protocol/messages/__init__.py
chuk_acp/protocol/messages/filesystem.py
chuk_acp/protocol/messages/initialize.py
chuk_acp/protocol/messages/send_message.py
chuk_acp/protocol/messages/session.py
chuk_acp/protocol/messages/terminal.py
chuk_acp/protocol/types/__init__.py
chuk_acp/protocol/types/capabilities.py
chuk_acp/protocol/types/commands.py
chuk_acp/protocol/types/content.py
chuk_acp/protocol/types/info.py
chuk_acp/protocol/types/mcp_servers.py
chuk_acp/protocol/types/permission.py
chuk_acp/protocol/types/plan.py
chuk_acp/protocol/types/session.py
chuk_acp/protocol/types/terminal.py
chuk_acp/protocol/types/tools.py
chuk_acp/transport/__init__.py
chuk_acp/transport/base.py
chuk_acp/transport/stdio.py
chuk_acp/utils/__init__.py
chuk_acp/utils/examples_finder.py
chuk_acp-0.3.2.data/data/share/chuk-acp/examples/README.md
chuk_acp-0.3.2.data/data/share/chuk-acp/examples/__init__.py
chuk_acp-0.3.2.data/data/share/chuk-acp/examples/agent_config.json
chuk_acp-0.3.2.data/data/share/chuk-acp/examples/claude_code_config.json
chuk_acp-0.3.2.data/data/share/chuk-acp/examples/code_helper_agent.py
chuk_acp-0.3.2.data/data/share/chuk-acp/examples/config_example.py
chuk_acp-0.3.2.data/data/share/chuk-acp/examples/echo_agent.py
chuk_acp-0.3.2.data/data/share/chuk-acp/examples/kimi_config.json
chuk_acp-0.3.2.data/data/share/chuk-acp/examples/quick_start.py
chuk_acp-0.3.2.data/data/share/chuk-acp/examples/simple_client.py
chuk_acp-0.3.2.data/data/share/chuk-acp/examples/standalone_agent.py
chuk_acp-0.3.2.data/data/share/chuk-acp/examples/zed_config.json
chuk_acp-0.3.2.dist-info/METADATA
chuk_acp-0.3.2.dist-info/WHEEL
chuk_acp-0.3.2.dist-info/entry_points.txt
chuk_acp-0.3.2.dist-info/RECORD
